Diamond_NAgg_Map/DiamondNAggMap.py
Diamond_NAgg_Map/__init__.py
Diamond_NAgg_Map/Quiddit_Spectra_Files/CAXBD.csv
Diamond_NAgg_Map/Quiddit_Spectra_Files/CAXBD.py
Diamond_NAgg_Map/Quiddit_Spectra_Files/CAXBD.xlsx
Diamond_NAgg_Map/Quiddit_Spectra_Files/CAXBDY.csv
Diamond_NAgg_Map/Quiddit_Spectra_Files/CAXBDY.py
Diamond_NAgg_Map/Quiddit_Spectra_Files/CAXBDY.xls
Diamond_NAgg_Map/Quiddit_Spectra_Files/__init__.py
Diamond_NAgg_Map/Quiddit_Spectra_Files/typeIIA.py
Diamond_NAgg_Map/Quiddit_Spectra_Files/typeIIa.csv
Diamond_NAgg_Map/Quiddit_Spectra_Files/typeIIa_Excel.csv
Diamond_NAgg_Map/Quiddit_Spectra_Files/typeIIa_Excel.xls
diamond_nagg_map-0.7.3.dist-info/METADATA
diamond_nagg_map-0.7.3.dist-info/WHEEL
diamond_nagg_map-0.7.3.dist-info/entry_points.txt
diamond_nagg_map-0.7.3.dist-info/RECORD
